[
  {
    "annotator": "i",
    "obj_id": "1",
    "obj_type": "Truck",
    "psr": {
      "position": {
        "x": -13.487539163585552,
        "y": -4.103134964415858,
        "z": -1.4211459816570997
      },
      "rotation": {
        "x": 0,
        "y": 0,
        "z": 0.005073204627638342
      },
      "scale": {
        "x": 5.740250334115569,
        "y": 2.2497663208776584,
        "z": 1.62004816532135
      }
    }
  },
  {
    "obj_id": "2",
    "obj_type": "Car",
    "psr": {
      "position": {
        "x": -24.527432600839514,
        "y": 2.329544299042614,
        "z": -1.4078970189668554
      },
      "rotation": {
        "x": 0,
        "y": 0,
        "z": 3.1393819701536554
      },
      "scale": {
        "x": 4.459672964268946,
        "y": 1.9193025239143588,
        "z": 1.5473792075533916
      }
    }
  },
  {
    "obj_id": "4",
    "obj_type": "Car",
    "psr": {
      "position": {
        "x": 3.654530063106904,
        "y": 3.248428209346912,
        "z": -0.9166548974829172
      },
      "rotation": {
        "x": 0,
        "y": 0,
        "z": -3.0736170983378566
      },
      "scale": {
        "x": 4.335196529137345,
        "y": 2.0019331822810895,
        "z": 1.5500932931900024
      }
    }
  },
  {
    "annotator": "i",
    "obj_id": "6",
    "obj_type": "Car",
    "psr": {
      "position": {
        "x": 12.168341221130959,
        "y": -3.543604438107991,
        "z": -0.3102565163744122
      },
      "rotation": {
        "x": 0,
        "y": 0,
        "z": 0.04384876746050074
      },
      "scale": {
        "x": 4.122622268966575,
        "y": 1.8372218635421511,
        "z": 1.7478507323520576
      }
    }
  },
  {
    "obj_id": "7",
    "obj_type": "Car",
    "psr": {
      "position": {
        "x": 5.924740649219486,
        "y": -3.7725906880352102,
        "z": -0.6156992303171467
      },
      "rotation": {
        "x": 0,
        "y": 0,
        "z": 0.013502495451690584
      },
      "scale": {
        "x": 4.307490331883766,
        "y": 1.9705455971068582,
        "z": 1.5947666475849767
      }
    }
  },
  {
    "obj_id": "8",
    "obj_type": "Car",
    "psr": {
      "position": {
        "x": -5.612883481370318,
        "y": 10.446493548148396,
        "z": -1.0456707407678214
      },
      "rotation": {
        "x": 0,
        "y": 0,
        "z": -1.5883079717201274
      },
      "scale": {
        "x": 4.233790556531471,
        "y": 1.832166733358159,
        "z": 1.5696326147167259
      }
    }
  }
]