[
  {
    "obj_id": "27",
    "obj_type": "Van",
    "psr": {
      "position": {
        "x": -9.468481260154817,
        "y": 5.730453017922628,
        "z": -1.219440433130683
      },
      "rotation": {
        "x": 0,
        "y": 0,
        "z": 3.090425281801077
      },
      "scale": {
        "x": 4.160571830516664,
        "y": 1.8769692691863638,
        "z": 1.6010933900731703
      }
    }
  },
  {
    "obj_id": "29",
    "obj_type": "Car",
    "psr": {
      "position": {
        "x": 2.5834439525820017,
        "y": 5.184383658581282,
        "z": -0.9471650201060537
      },
      "rotation": {
        "x": 0,
        "y": 0,
        "z": 3.0796992632068494
      },
      "scale": {
        "x": 4.409609986144041,
        "y": 1.8740734428262702,
        "z": 1.410065248525202
      }
    }
  },
  {
    "obj_id": "30",
    "obj_type": "Car",
    "psr": {
      "position": {
        "x": -3.819659051204029,
        "y": 5.1947957902806285,
        "z": -1.2052516681809549
      },
      "rotation": {
        "x": 0,
        "y": 0,
        "z": 3.1311609629146693
      },
      "scale": {
        "x": 4.301849689984319,
        "y": 1.6696957408283797,
        "z": 1.3452908843420979
      }
    }
  }
]