[
  {
    "obj_id": "1",
    "obj_type": "Truck",
    "psr": {
      "position": {
        "x": -4.08838133700264,
        "y": -4.286880520508983,
        "z": -0.9851264994498157
      },
      "rotation": {
        "x": 0,
        "y": 0,
        "z": 0.01404801217988851
      },
      "scale": {
        "x": 6.040964811455932,
        "y": 2.542334138256258,
        "z": 1.797612540314242
      }
    }
  },
  {
    "obj_id": "2",
    "obj_type": "Car",
    "psr": {
      "position": {
        "x": -15.35279353067483,
        "y": 2.4182180948205314,
        "z": -1.1471361480265094
      },
      "rotation": {
        "x": 0,
        "y": 0,
        "z": -3.1234402772863197
      },
      "scale": {
        "x": 4.459672964268946,
        "y": 1.9193025239143588,
        "z": 1.5473792075533916
      }
    }
  },
  {
    "annotator": "i",
    "obj_id": "3",
    "obj_type": "Car",
    "psr": {
      "position": {
        "x": -10.736138039766274,
        "y": -4.22889598788629,
        "z": -1.3612010900967628
      },
      "rotation": {
        "x": 0,
        "y": 0,
        "z": 0.010931373827073907
      },
      "scale": {
        "x": 4.15359582927006,
        "y": 1.6837709734772748,
        "z": 1.2835370559107424
      }
    }
  },
  {
    "annotator": "i",
    "obj_id": "4",
    "obj_type": "Car",
    "psr": {
      "position": {
        "x": 12.719728778399599,
        "y": 3.312518201213834,
        "z": -0.46295182860033157
      },
      "rotation": {
        "x": 0,
        "y": 0,
        "z": 3.1322815719905854
      },
      "scale": {
        "x": 3.6878504011934696,
        "y": 1.7345945992819412,
        "z": 0.9843078255653381
      }
    }
  },
  {
    "obj_id": "6",
    "obj_type": "Car",
    "psr": {
      "position": {
        "x": 21.82039949483935,
        "y": -3.2026382587408637,
        "z": -0.08669754963270596
      },
      "rotation": {
        "x": 0,
        "y": 0,
        "z": 0.07743889105656543
      },
      "scale": {
        "x": 4.190317837123432,
        "y": 1.6620547490877504,
        "z": 1.5461776813675074
      }
    }
  },
  {
    "obj_id": "7",
    "obj_type": "Car",
    "psr": {
      "position": {
        "x": 15.464460660519308,
        "y": -3.5724621454323824,
        "z": -0.39727901458740206
      },
      "rotation": {
        "x": 0,
        "y": 0,
        "z": 0.04358190688612725
      },
      "scale": {
        "x": 4.14139173296794,
        "y": 1.7202943875323813,
        "z": 1.5211620330810547
      }
    }
  },
  {
    "annotator": "i",
    "obj_id": "8",
    "obj_type": "Car",
    "psr": {
      "position": {
        "x": 3.4219045581534147,
        "y": 10.219862947615184,
        "z": -0.3926525837560372
      },
      "rotation": {
        "x": 0,
        "y": 0,
        "z": -1.6170192313526586
      },
      "scale": {
        "x": 3.9068358961784253,
        "y": 1.8801049297458388,
        "z": 1.762089651302312
      }
    }
  }
]