[
  {
    "obj_id": "21",
    "obj_type": "Van",
    "psr": {
      "position": {
        "x": -18.78609469384992,
        "y": 10.778534379643588,
        "z": -1.0367947017980645
      },
      "rotation": {
        "x": 0,
        "y": 0,
        "z": -1.5266782818139242
      },
      "scale": {
        "x": 7.624593284577426,
        "y": 2.3496829685117024,
        "z": 3.043726204265362
      }
    }
  },
  {
    "obj_id": "23",
    "obj_type": "Car",
    "psr": {
      "position": {
        "x": 22.834282004762827,
        "y": 4.794357035385474,
        "z": -0.25668771263533713
      },
      "rotation": {
        "x": 0,
        "y": 0,
        "z": 3.1153366118242305
      },
      "scale": {
        "x": 4.548529338591605,
        "y": 1.77816634009573,
        "z": 1.6038244079295536
      }
    }
  }
]