[
  {
    "obj_id": "23",
    "obj_type": "Car",
    "psr": {
      "position": {
        "x": -19.073932884326496,
        "y": 4.235581822236782,
        "z": -1.7771603534828184
      },
      "rotation": {
        "x": 0,
        "y": 0,
        "z": 3.140559801105331
      },
      "scale": {
        "x": 4.548529338591605,
        "y": 1.9001612188262065,
        "z": 1.453617007155571
      }
    }
  },
  {
    "obj_id": "24",
    "obj_type": "Car",
    "psr": {
      "position": {
        "x": 17.01880067912225,
        "y": 5.194732211693008,
        "z": -0.5610403227806078
      },
      "rotation": {
        "x": 0,
        "y": 0,
        "z": -3.115412714809878
      },
      "scale": {
        "x": 4.5311978164781035,
        "y": 1.8401587377609998,
        "z": 1.482918381690979
      }
    }
  }
]