[
  {
    "obj_id": "24",
    "obj_type": "Car",
    "psr": {
      "position": {
        "x": -11.531511889703324,
        "y": 5.117200710817997,
        "z": -1.6972347647644492
      },
      "rotation": {
        "x": 0,
        "y": 0,
        "z": -3.0817396765860625
      },
      "scale": {
        "x": 4.5311978164781035,
        "y": 1.8401587377609998,
        "z": 1.5017388675118455
      }
    }
  },
  {
    "obj_id": "26",
    "obj_type": "Car",
    "psr": {
      "position": {
        "x": -2.2884280338066674,
        "y": 5.524518661877664,
        "z": -1.2185786080568817
      },
      "rotation": {
        "x": 0,
        "y": 0,
        "z": -3.0634038912697528
      },
      "scale": {
        "x": 4.070247971815126,
        "y": 1.7620214728693533,
        "z": 1.5232230419007493
      }
    }
  },
  {
    "obj_id": "27",
    "obj_type": "Van",
    "psr": {
      "position": {
        "x": 3.3325138707614315,
        "y": 5.573240063945377,
        "z": -0.9020476250753856
      },
      "rotation": {
        "x": 0,
        "y": 0,
        "z": -3.1153656682010777
      },
      "scale": {
        "x": 4.160571830516664,
        "y": 1.8769692691863638,
        "z": 1.6010933900731703
      }
    }
  },
  {
    "obj_id": "29",
    "obj_type": "Car",
    "psr": {
      "position": {
        "x": 15.391249888059868,
        "y": 6.054253968953433,
        "z": -0.6832256898268763
      },
      "rotation": {
        "x": 0,
        "y": 0,
        "z": 3.1241214161436166
      },
      "scale": {
        "x": 4.409609986144041,
        "y": 2.003213524043705,
        "z": 1.4537017270715809
      }
    }
  },
  {
    "obj_id": "30",
    "obj_type": "Car",
    "psr": {
      "position": {
        "x": 8.797798234618321,
        "y": 5.607930284612648,
        "z": -1.1412273738639718
      },
      "rotation": {
        "x": -0.052341876419537345,
        "y": -0.0013734897344379186,
        "z": -3.1153818907005673
      },
      "scale": {
        "x": 4.301849689984319,
        "y": 1.6321905084109511,
        "z": 1.3452908843420979
      }
    }
  }
]