[
  {
    "obj_id": "27",
    "obj_type": "Van",
    "psr": {
      "position": {
        "x": -10.928934393577908,
        "y": 5.607763942680472,
        "z": -1.4344486200951696
      },
      "rotation": {
        "x": 0,
        "y": 0,
        "z": 3.107016947273062
      },
      "scale": {
        "x": 4.160571830516664,
        "y": 1.8769692691863638,
        "z": 1.6010933900731703
      }
    }
  },
  {
    "obj_id": "29",
    "obj_type": "Car",
    "psr": {
      "position": {
        "x": 1.0804259025280771,
        "y": 5.153342575357101,
        "z": -0.9658666473165081
      },
      "rotation": {
        "x": 0,
        "y": 0,
        "z": 3.090183202002972
      },
      "scale": {
        "x": 4.36766155528726,
        "y": 1.8740734428262702,
        "z": 1.410065248525202
      }
    }
  },
  {
    "obj_id": "30",
    "obj_type": "Car",
    "psr": {
      "position": {
        "x": -5.302697864255606,
        "y": 5.210510688582872,
        "z": -1.3258020156928958
      },
      "rotation": {
        "x": 0,
        "y": 0,
        "z": 3.1361381994608424
      },
      "scale": {
        "x": 4.301849689984319,
        "y": 1.6696957408283797,
        "z": 1.3452908843420979
      }
    }
  }
]