[
  {
    "obj_id": "24",
    "obj_type": "Car",
    "psr": {
      "position": {
        "x": -17.821267437589995,
        "y": 5.22082472159218,
        "z": -1.7986076520619112
      },
      "rotation": {
        "x": 0,
        "y": 0,
        "z": -3.1240495404309256
      },
      "scale": {
        "x": 4.5311978164781035,
        "y": 1.8401587377609998,
        "z": 1.5456533344272012
      }
    }
  },
  {
    "obj_id": "26",
    "obj_type": "Car",
    "psr": {
      "position": {
        "x": -8.336706774334743,
        "y": 5.586441256660692,
        "z": -1.5341401075134398
      },
      "rotation": {
        "x": 0,
        "y": 0,
        "z": -3.067304872653916
      },
      "scale": {
        "x": 4.070247971815126,
        "y": 1.7620214728693533,
        "z": 1.2822983235555663
      }
    }
  },
  {
    "obj_id": "27",
    "obj_type": "Van",
    "psr": {
      "position": {
        "x": -2.6990223150351085,
        "y": 5.5233228907191005,
        "z": -1.0531659213685731
      },
      "rotation": {
        "x": 0,
        "y": 0,
        "z": -3.115288610742855
      },
      "scale": {
        "x": 4.160571830516664,
        "y": 1.8769692691863638,
        "z": 1.6010933900731703
      }
    }
  },
  {
    "obj_id": "29",
    "obj_type": "Car",
    "psr": {
      "position": {
        "x": 9.199239233857899,
        "y": 5.746532119250766,
        "z": -0.8983585112642366
      },
      "rotation": {
        "x": 0,
        "y": 0,
        "z": 3.1241573059960825
      },
      "scale": {
        "x": 4.409609986144041,
        "y": 1.8740734428262702,
        "z": 1.354452281259472
      }
    }
  },
  {
    "obj_id": "30",
    "obj_type": "Car",
    "psr": {
      "position": {
        "x": 2.6715258368269077,
        "y": 5.422985433468859,
        "z": -1.1256920971397553
      },
      "rotation": {
        "x": 0,
        "y": 0,
        "z": -3.115424668922618
      },
      "scale": {
        "x": 4.301849689984319,
        "y": 1.644692252550094,
        "z": 1.3452908843420979
      }
    }
  }
]